odoo/addons/edi_voxel/README.rst
odoo/addons/edi_voxel/__init__.py
odoo/addons/edi_voxel/__manifest__.py
odoo/addons/edi_voxel/data/data_voxel_uom.xml
odoo/addons/edi_voxel/i18n/edi_voxel.pot
odoo/addons/edi_voxel/i18n/es.po
odoo/addons/edi_voxel/models/__init__.py
odoo/addons/edi_voxel/models/account.py
odoo/addons/edi_voxel/models/queue_job.py
odoo/addons/edi_voxel/models/res_company.py
odoo/addons/edi_voxel/models/res_config_settings.py
odoo/addons/edi_voxel/models/res_partner.py
odoo/addons/edi_voxel/models/uom_uom.py
odoo/addons/edi_voxel/models/voxel_login.py
odoo/addons/edi_voxel/models/voxel_mixin.py
odoo/addons/edi_voxel/readme/CONTRIBUTORS.rst
odoo/addons/edi_voxel/readme/DESCRIPTION.rst
odoo/addons/edi_voxel/security/ir.model.access.csv
odoo/addons/edi_voxel/security/voxel_security.xml
odoo/addons/edi_voxel/static/description/icon.png
odoo/addons/edi_voxel/static/description/index.html
odoo/addons/edi_voxel/views/account_tax_views.xml
odoo/addons/edi_voxel/views/product_uom_views.xml
odoo/addons/edi_voxel/views/res_company_view.xml
odoo/addons/edi_voxel/views/res_config_settings_views.xml
odoo/addons/edi_voxel/views/res_partner_views.xml
odoo/addons/edi_voxel/views/template_voxel_report.xml
odoo/addons/edi_voxel/views/voxel_login_views.xml
odoo13_addon_edi_voxel-13.0.1.0.2.dist-info/METADATA
odoo13_addon_edi_voxel-13.0.1.0.2.dist-info/WHEEL
odoo13_addon_edi_voxel-13.0.1.0.2.dist-info/top_level.txt
odoo13_addon_edi_voxel-13.0.1.0.2.dist-info/RECORD
