Metadata-Version: 2.1
Name: odoo13-addon-edi-voxel
Version: 13.0.1.0.2
Summary: Base module for connecting with Voxel
Home-page: https://github.com/OCA/edi
Author: Tecnativa, Odoo Community Association (OCA)
Author-email: support@odoo-community.org
License: AGPL-3
Platform: UNKNOWN
Classifier: Programming Language :: Python
Classifier: Framework :: Odoo
Classifier: Framework :: Odoo :: 13.0
Classifier: License :: OSI Approved :: GNU Affero General Public License v3
Requires-Python: >=3.5
Requires-Dist: odoo13-addon-base-iso3166
Requires-Dist: odoo13-addon-product-supplierinfo-for-customer
Requires-Dist: odoo13-addon-queue-job
Requires-Dist: odoo13-addon-report-xml
Requires-Dist: odoo (<13.1dev,>=13.0a)
